Metadata-Version: 2.1
Name: veriloga
Version: 0.0.1
Summary: pyadms: Verilog-A Compiler
Home-page: https://github.com/pyadms/pyadms
Author: Juan Sanchez
Author-email: info@devsim.com
License: GPL 2.0
Project-URL: Bug Tracker, https://github.com/pyadms/pyadms/issues
Project-URL: Source Code, https://github.com/pyadms/pyadms
Classifier: Development Status :: 3 - Alpha
Classifier: Intended Audience :: Science/Research
Classifier: License :: OSI Approved :: Apache Software License
Classifier: Programming Language :: Python :: 3
Classifier: Topic :: Scientific/Engineering :: Electronic Design Automation (EDA)
License-File: COPYING
License-File: NOTICE
